viewephys/__init__.py
viewephys/command_line.py
viewephys/gui.py
viewephys/nav_file.ui
viewephys/raster.py
viewephys/raster.ui
viewephys/viewephys.svg
viewephys-1.0.1.dist-info/LICENSE
viewephys-1.0.1.dist-info/METADATA
viewephys-1.0.1.dist-info/WHEEL
viewephys-1.0.1.dist-info/entry_points.txt
viewephys-1.0.1.dist-info/top_level.txt
viewephys-1.0.1.dist-info/RECORD
