Metadata-Version: 2.1
Name: viewephys
Version: 1.0.1
Summary: Raw Neuropixel data viewer for numpy
Home-page: https://github.com/int-brain-lab/viewephys
Author: Olivier Winter
Project-URL: Bug Tracker, https://github.com/int-brain-lab/viewephys/issues
Classifier: Programming Language :: Python :: 3
Classifier: License :: OSI Approved :: MIT License
Classifier: Operating System :: OS Independent
Requires-Python: >=3.10
License-File: LICENSE
Requires-Dist: easyqc>=0.7.0
Requires-Dist: ibl-neuropixel>=1.0.1
Requires-Dist: ibllib
Requires-Dist: iblutil>=1.6.0
Requires-Dist: pandas
